itkdb_gtk/CreateShipments.py
itkdb_gtk/GetShipments.py
itkdb_gtk/GlueWeight.py
itkdb_gtk/ITkDB.desktop
itkdb_gtk/ITkDB.svg
itkdb_gtk/ITkDBlogin.py
itkdb_gtk/ITkDButils.py
itkdb_gtk/PanelVisualInspection.py
itkdb_gtk/QRScanner.py
itkdb_gtk/SensorUtils.py
itkdb_gtk/ShowAttachments.py
itkdb_gtk/ShowComments.py
itkdb_gtk/ShowDefects.py
itkdb_gtk/UploadModuleIV.py
itkdb_gtk/UploadMultipleTests.py
itkdb_gtk/UploadTest.py
itkdb_gtk/VisualInspection.py
itkdb_gtk/WireBondGui.py
itkdb_gtk/__init__.py
itkdb_gtk/dashBoard.py
itkdb_gtk/dbGtkUtils.py
itkdb_gtk/findComponent.py
itkdb_gtk/findVTRx.py
itkdb_gtk/readGoogleSheet.py
itkdb_gtk/untrash_component.py
itkdb_gtk-0.21.0.dist-info/METADATA
itkdb_gtk-0.21.0.dist-info/WHEEL
itkdb_gtk-0.21.0.dist-info/entry_points.txt
itkdb_gtk-0.21.0.dist-info/top_level.txt
itkdb_gtk-0.21.0.dist-info/RECORD
