Metadata-Version: 2.4
Name: itkdb_gtk
Version: 0.21.0
Summary: A collection of Gtk based GUI to access ITkDB.
Author-email: Carlos Lacasta <carlos.lacasta@cern.ch>
Project-URL: Homepage, https://gitlab.cern.ch/atlas-itk/sw/db/itk-pdb-gtk-gui-utils
Project-URL: Bug Tracker, https://gitlab.cern.ch/atlas-itk/sw/db/itk-pdb-gtk-gui-utils/-/issues
Classifier: Programming Language :: Python :: 3
Classifier: Operating System :: OS Independent
Requires-Python: >=3.7
Requires-Dist: itkdb>=0.4.0
Requires-Dist: numpy
Requires-Dist: matplotlib
Requires-Dist: openpyxl
Requires-Dist: pyserial
Requires-Dist: python_dateutil
Requires-Dist: requests
Requires-Dist: PyGObject
